AUTHORS
COPYING
MANIFEST.in
README
ez_setup.py
setup.cfg
setup.py
examples/test.py
include/lightmediascanner/c_lightmediascanner.pxd
lightmediascanner/__init__.py
lightmediascanner/lightmediascanner.c_lightmediascanner.pyx
python_lightmediascanner.egg-info/PKG-INFO
python_lightmediascanner.egg-info/SOURCES.txt
python_lightmediascanner.egg-info/dependency_links.txt
python_lightmediascanner.egg-info/native_libs.txt
python_lightmediascanner.egg-info/not-zip-safe
python_lightmediascanner.egg-info/top_level.txt