Metadata-Version: 1.0
Name: python-lightmediascanner
Version: 0.2.0
Summary: Python bindings for Light Media Scanner
Home-page: UNKNOWN
Author: Gustavo Sverzut Barbieri
Author-email: barbieri@profusion.mobi
License: LGPL
Keywords: wrapper binding media scanner
Platform: UNKNOWN
Classifier: Development Status :: 3 - Alpha
Classifier: Intended Audience :: Developers
Classifier: License :: OSI Approved :: GNU Library or Lesser General Public License (LGPL)
Classifier: Operating System :: MacOS :: MacOS X
Classifier: Operating System :: POSIX
Classifier: Programming Language :: C
Classifier: Programming Language :: Python
Classifier: Topic :: Software Development :: Libraries :: Python Modules
